ohmyscrapper/__init__.py
ohmyscrapper/__main__.py
ohmyscrapper/core/config.py
ohmyscrapper/core/config_files.py
ohmyscrapper/core/default_files/config.yaml
ohmyscrapper/core/default_files/url_sniffing.yaml
ohmyscrapper/core/default_files/url_types.yaml
ohmyscrapper/models/urls_manager.py
ohmyscrapper/modules/browser.py
ohmyscrapper/modules/classify_urls.py
ohmyscrapper/modules/load_txt.py
ohmyscrapper/modules/merge_dbs.py
ohmyscrapper/modules/process_with_ai.py
ohmyscrapper/modules/scrap_urls.py
ohmyscrapper/modules/seed.py
ohmyscrapper/modules/show.py
ohmyscrapper/modules/sniff_url.py
ohmyscrapper/modules/untouch_all.py
ohmyscrapper-0.8.2.dist-info/WHEEL
ohmyscrapper-0.8.2.dist-info/entry_points.txt
ohmyscrapper-0.8.2.dist-info/METADATA
ohmyscrapper-0.8.2.dist-info/RECORD
