Metadata-Version: 2.4
Name: ohmyscrapper
Version: 0.8.2
Summary: OhMyScrapper scrapes texts and urls looking for links and jobs-data to create a final report with general information about job positions.
Author: Cesar Cardoso
Author-email: Cesar Cardoso <hello@cesarcardoso.cc>
License-Expression: MIT
Requires-Dist: beautifulsoup4>=4.14.3
Requires-Dist: google-genai>=1.55.0
Requires-Dist: markdown>=3.10
Requires-Dist: pandas>=2.3.3
Requires-Dist: python-dotenv>=1.2.1
Requires-Dist: pyyaml>=6.0.3
Requires-Dist: requests>=2.32.5
Requires-Dist: rich>=14.2.0
Requires-Dist: selenium>=4.39.0
Requires-Dist: urlextract>=1.9.0
Requires-Python: >=3.11
Project-URL: Changelog, https://github.com/bouli/ohmyscrapper/releases/latest
Project-URL: Repository, https://github.com/bouli/ohmyscrapper
